setup.py
MarkovPy.egg-info/PKG-INFO
MarkovPy.egg-info/SOURCES.txt
MarkovPy.egg-info/dependency_links.txt
MarkovPy.egg-info/top_level.txt
markov/__init__.py
markov/markov.py
markov/test_markov.py
markov/test_prepare.py
markov/test_stores.py
markov/stores/__init__.py
markov/stores/pickle.py
markov/stores/redis.py
markov/stores/sqlite.py
markov/stores/store.py