Metadata-Version: 1.1
Name: MarkovPy
Version: 0.5.10
Summary: A simple Markovchain-Implementation
Home-page: https://github.com/Thor77/MarkovPy
Author: Thor77
Author-email: thor77@thor77.org
License: MIT
Keywords: markovpy markov ai
Platform: UNKNOWN
Classifier: Intended Audience :: Developers
Classifier: License :: OSI Approved :: MIT License
Classifier: Programming Language :: Python :: 3.4
Classifier: Topic :: Communications :: Chat
Classifier: Topic :: Database
Classifier: Topic :: Documentation :: Sphinx
Classifier: Topic :: Scientific/Engineering :: Artificial Intelligence
